authenta/__init__.py
authenta/async_authenta_client.py
authenta/authenta_client.py
authenta/authenta_exceptions.py
authenta/visualization.py
authenta-0.2.2.dist-info/.ipynb_checkpoints/PKG-INFO-checkpoint
authenta-0.2.2.dist-info/.ipynb_checkpoints/SOURCES-checkpoint.txt
authenta-0.2.2.dist-info/.ipynb_checkpoints/dependency_links-checkpoint.txt
authenta-0.2.2.dist-info/.ipynb_checkpoints/requires-checkpoint.txt
authenta-0.2.2.dist-info/.ipynb_checkpoints/top_level-checkpoint.txt
authenta-0.2.2.dist-info/METADATA
authenta-0.2.2.dist-info/WHEEL
authenta-0.2.2.dist-info/top_level.txt
authenta-0.2.2.dist-info/RECORD
