Metadata-Version: 2.4
Name: authenta
Version: 0.2.2
Summary: Python SDK for the Authenta API to detect deepfakes and manipulated media
Home-page: https://github.com/phospheneai/authenta-python-sdk
Author: Arjun Adhithya
Author-email: rrarjunadhithya@gmail.com
License: MIT
Classifier: Programming Language :: Python :: 3
Classifier: Programming Language :: Python :: 3.8
Classifier: Programming Language :: Python :: 3.9
Classifier: Programming Language :: Python :: 3.10
Classifier: Operating System :: OS Independent
Requires-Python: >=3.8
Requires-Dist: requests>=2.20.0
